gravitasml/__init__.py
gravitasml/parser.py
gravitasml/token.py
gravitasml-0.1.4.dist-info/METADATA
gravitasml-0.1.4.dist-info/WHEEL
gravitasml-0.1.4.dist-info/licenses/LICENSE
gravitasml-0.1.4.dist-info/RECORD
