Metadata-Version: 2.4
Name: gravitasml
Version: 0.1.4
Summary: 
License-File: LICENSE
Author: Nicholas Tindle
Author-email: nicholas.tindle@agpt.co
Requires-Python: >=3.10,<4.0
Classifier: Framework :: Pydantic :: 2
Classifier: Intended Audience :: Developers
Classifier: License :: OSI Approved :: MIT License
Classifier: Natural Language :: English
Classifier: Operating System :: OS Independent
Classifier: Programming Language :: Python :: 3
Classifier: Programming Language :: Python :: 3.10
Classifier: Programming Language :: Python :: 3.11
Classifier: Programming Language :: Python :: 3.12
Classifier: Programming Language :: Python :: 3.13
Classifier: Programming Language :: Python :: 3.14
Classifier: Topic :: Text Processing :: Markup
Classifier: Typing :: Typed
Requires-Dist: black (>=24.10.0,<25.0.0)
Requires-Dist: pydantic (>=2.9.2,<3.0.0)
Requires-Dist: pytest (>=8.2.1,<9.0.0)
Project-URL: Homepage, https://github.com/significant-gravitas/
